{
    "out": "docs-create/docs",
    "inputFiles": [
        "./src/index.ts"
        //"./src/create/cubic-through-point.ts"
        //"./src/boxes/are-boxes-intersecting.ts"
        //"./src/global-properties/bounds/get-bounding-box-.ts"
    ],
    "mdxFolder": "docs-create/docs/mdx",
    "exclude": [
        "**/experiments"
    ],
    "excludePrivate": false,
    "hideBreadcrumbs": true,
    "stripInternal": true,
    "publicPath": "",
    "excludeTags": ["implementationDetails"],
    "tsconfig": "c:/projects/bezier/tsconfig.json"
}
